pydantic_yaml_parser/__init__.py
pydantic_yaml_parser/_modidx.py
pydantic_yaml_parser/yaml.py
pydantic_yaml_parser-0.0.4.dist-info/LICENSE
pydantic_yaml_parser-0.0.4.dist-info/METADATA
pydantic_yaml_parser-0.0.4.dist-info/WHEEL
pydantic_yaml_parser-0.0.4.dist-info/entry_points.txt
pydantic_yaml_parser-0.0.4.dist-info/top_level.txt
pydantic_yaml_parser-0.0.4.dist-info/RECORD
