Metadata-Version: 2.1
Name: pydantic-yaml-parser
Version: 0.0.4
Summary: parse yaml files with pydantic
Home-page: https://github.com/hamelsmu/pydantic-yaml-parser
Author: Hamel Husain
Author-email: hamel.husain@gmail.com
License: Apache Software License 2.0
Keywords: pydantic yaml
Platform: UNKNOWN
Classifier: Development Status :: 4 - Beta
Classifier: Intended Audience :: Developers
Classifier: Natural Language :: English
Classifier: Programming Language :: Python :: 3.7
Classifier: Programming Language :: Python :: 3.8
Classifier: Programming Language :: Python :: 3.9
Classifier: Programming Language :: Python :: 3.10
Classifier: License :: OSI Approved :: Apache Software License
Requires-Python: >=3.7
License-File: LICENSE
Requires-Dist: fastcore
Requires-Dist: pydantic
Requires-Dist: pyyaml
Provides-Extra: dev
